{
    "scans": {
        "begivenhed": [
            "Billedkunst",
            "Tysk",
            "Billedkunst",
            "Billedkunst",
            "Tysk",
            "Tysk",
            "Tysk",
            "Tysk",
            "Fysik/kemi",
            "Biologi",
            "Tysk",
            "Historie",
            "Tysk",
            "Fysik/kemi",
            "Biologi",
            "Historie",
            "Tysk",
            "Tysk"
        ],
        "beskrivelse": [
            "\nKunstv\u00e6rket og stedet\n\nI skal til i dag v\u00e6re f\u00e6rdige med jeres kunstv\u00e6rk, hvor I taget udgangspunkt i analysen af stedet. I skal freml\u00e6gge det hele ud fra et slideshow inkl. jeres v\u00e6rk (ikke hvis det er udstillet), hvor I beskriver stedet, kunstv\u00e6rket og processen. Alt dokumenteres med indsatte billeder og tekst. Husk at f\u00e5 billeder af stedet, hvor jeres kunstv\u00e6rk er udstillet i det udvalgte rum.\nI skal dokumentere hvilke kunstnere, der har lavet lignende  (b\u00e5de udformning og materialevalg) - husk navne og billeder. ",
            "\nDer Sprung, S. 82-85. LYT  2 gange (uden bog og med bog). \u00d8v opl\u00e6sning og overs\u00e6ttelse (gentagelse fra i torsdags)",
            "\nKunstv\u00e6rket og stedet \nOBS.. uds\u00e6ttes til at v\u00e6re f\u00e6rdiggjort til mandag den 7. juni\n\nI skal til i dag v\u00e6re f\u00e6rdige med jeres kunstv\u00e6rk, hvor I taget udgangspunkt i analysen af stedet. I skal freml\u00e6gge det hele ud fra et slideshow inkl. jeres v\u00e6rk (ikke hvis det er udstillet), hvor I beskriver stedet, kunstv\u00e6rket og processen. Alt dokumenteres med indsatte billeder og tekst. Husk at f\u00e5 billeder af stedet, hvor jeres kunstv\u00e6rk er udstillet i det udvalgte rum.\nI skal dokumentere hvilke kunstnere, der har lavet lignende  (b\u00e5de udformning og materialevalg) - husk navne og billeder. ",
            "\n\nI skal til i dag v\u00e6re f\u00e6rdige med jeres kunstv\u00e6rk, hvor I taget udgangspunkt i analysen af stedet. I skal freml\u00e6gge det hele ud fra et slideshow inkl. jeres v\u00e6rk (ikke hvis det er udstillet), hvor I beskriver stedet, kunstv\u00e6rket og processen. Alt dokumenteres med indsatte billeder og tekst. Husk at f\u00e5 billeder af stedet, hvor jeres kunstv\u00e6rk er udstillet i det udvalgte rum.\nI skal dokumentere hvilke kunstnere, der har lavet lignende (b\u00e5de udformning og materialevalg) - husk navne og billeder. \n",
            "\n\u00d8v Quizlet: https://quizlet.com/570338670/essen-und-trinken-flash-cards/\nSkriv de ord ned i gloseh\u00e6ftet, som er nye for jer (p\u00e5 tysk og dansk)",
            "\n\u00d8v Quizlet: https://quizlet.com/_9win48?x=1qqt&amp;i=2vbz10\nSkriv de ord ned i gloseh\u00e6ftet, som er nye for jer (p\u00e5 tysk og dansk)\n1) Flashcards\n2) Learn",
            "\n1) Haben i nutid og datid inkl. overs\u00e6ttelse p\u00e5 side 2\n2) Der Sprung:  s. 53 und 54, opgave 1 + Skriv ned i opgave 2: Zum Fr esse ich gern ......, und ich trinke gern .......",
            "\nDer Sprung,  s. 56 og 57",
            "\nl\u00e6se s-51-57 i fysikbog 2 p\u00e5 Verdens naturfag Husk at se de sm\u00e5 film der h\u00f8rer til",
            "\nVerdens naturfag biologibog 3.\nl\u00e6se biologibog 3 side 110-117",
            "\nTextbuch s. 6 og 7 - opl\u00e6sning og overs\u00e6ttelse",
            "\nLav opgaven: Lenin om opbygning af et socialistisk samfund\n\nLink: https://historie.gyldendal.dk/learningObject/3783fb3a-f269-4f7b-a30d-2f7ae73baf98",
            "\n s. 5: Kreuzwortr (p\u00e5 kopi eller i h\u00e6ftet).",
            "\nhttps://i-bog.gyldendal.dk/b95d9c2e-2975-4960-b8da-1a4178f44352#/?view=default&amp;page=61\nl\u00e6se side 58-67 i bog 2 fysik.",
            "\nl\u00e6se side 118-121 i biologibog 3 Verdens naturfag",
            "\nL\u00e6s afsnittene: USA og kapitalismen, USA dominans fra 1945 og Amerikansk livsstil\nLink: https://historie.gyldendal.dk/forloeb/den-kolde-krig/kapitler/03-hvad-er-den-kolde-krig/03-det-amerikanske-system",
            "\nTB, Opgave s. 10, skriftligt\nTB, L\u00e6s og overs\u00e6t side 11: Lyt, L\u00e6s og Lyt/l\u00e6s [Spor 3: Lyt til teksten (s. 11) - Side - Der Sprung none - Alinea](https://dersprung.alinea.dk/course/rI5H-der-sprung-4/page/r5us-lyt-til-teksten)",
            "\nGut Gemacht, s. 15"
        ],
        "author": [
            "20. aug 11:09 by Jacob Albrechtsen",
            "21. aug 18:09 by Birte Holst Andersen",
            "19. aug 12:37 by Anne-Mette Hessel",
            "25. aug 13:34 by Birte Holst Andersen",
            "29. aug 21:07 by Jens Jacob Zachariassen"
        ],
        "files": [
            "None",
            "None",
            "None",
            "None",
            "None"
        ],
        "tidspunkt": [
            "31. maj 10:10",
            "27. maj 12:10",
            "31. maj 10:10",
            "7. jun 10:10",
            "3. jun 12:10",
            "3. jun 12:10",
            "7. jun 12:55",
            "10. jun 12:10",
            "13. aug 08:10",
            "19. aug 12:00",
            "17. aug 12:00",
            "20. aug 10:45",
            "19. aug 12:50",
            "20. aug 08:10",
            "26. aug 12:00",
            "23. aug 10:45",
            "24. aug 12:00",
            "26. aug 12:50"
        ],
        "file_names": [
            "None",
            "None",
            "None",
            "None",
            "None"
        ],
        "url": [
            "https://nr-aadal.viggo.dk/Basic/HomeworkAndAssignment/Details/1701/#modal",
            "https://nr-aadal.viggo.dk/Basic/HomeworkAndAssignment/Details/1707/#modal",
            "https://nr-aadal.viggo.dk/Basic/HomeworkAndAssignment/Details/1701/#modal",
            "https://nr-aadal.viggo.dk/Basic/HomeworkAndAssignment/Details/1711/#modal",
            "https://nr-aadal.viggo.dk/Basic/HomeworkAndAssignment/Details/1714/#modal",
            "https://nr-aadal.viggo.dk/Basic/HomeworkAndAssignment/Details/1714/#modal",
            "https://nr-aadal.viggo.dk/Basic/HomeworkAndAssignment/Details/1717/#modal",
            "https://nr-aadal.viggo.dk/Basic/HomeworkAndAssignment/Details/1722/#modal",
            "https://nr-aadal.viggo.dk/Basic/HomeworkAndAssignment/Details/1729/#modal",
            "https://nr-aadal.viggo.dk/Basic/HomeworkAndAssignment/Details/1730/#modal",
            "https://nr-aadal.viggo.dk/Basic/HomeworkAndAssignment/Details/1736/#modal",
            "https://nr-aadal.viggo.dk/Basic/HomeworkAndAssignment/Details/1737/#modal",
            "https://nr-aadal.viggo.dk/Basic/HomeworkAndAssignment/Details/1748/#modal",
            "https://nr-aadal.viggo.dk/Basic/HomeworkAndAssignment/Details/1750/#modal",
            "https://nr-aadal.viggo.dk/Basic/HomeworkAndAssignment/Details/1752/#modal",
            "https://nr-aadal.viggo.dk/Basic/HomeworkAndAssignment/Details/1760/#modal",
            "https://nr-aadal.viggo.dk/Basic/HomeworkAndAssignment/Details/1762/#modal",
            "https://nr-aadal.viggo.dk/Basic/HomeworkAndAssignment/Details/1774/#modal",
            "https://nr-aadal.viggo.dk/Basic/HomeworkAndAssignment/Details/1760/#modal",
            "https://nr-aadal.viggo.dk/Basic/HomeworkAndAssignment/Details/1762/#modal",
            "https://nr-aadal.viggo.dk/Basic/HomeworkAndAssignment/Details/1752/#modal",
            "https://nr-aadal.viggo.dk/Basic/HomeworkAndAssignment/Details/1774/#modal",
            "https://nr-aadal.viggo.dk/Basic/HomeworkAndAssignment/Details/1780/#modal"
        ],
        "subject": [
            "Historie",
            "Tysk",
            "Biologi",
            "Tysk",
            "Samfundsfag"
        ],
        "description": [
            "\ne28099s\n https://historie.gyldendal.dk/forloeb/den-kolde-krig/kapitler/03-hvad-er-den-kolde-krig/03-det-amerikanske-system",
            "\n\n Alinea",
            "\n naturfag",
            "\n 15",
            "\n-bogsp\u00f8rgsm\u00e5l77(de4f\u00f8rsteog8sidste)Deadlinefredag10-9\n"
        ],
        "time": [
            "23. aug 10:45",
            "24. aug 12:00",
            "26. aug 12:00",
            "26. aug 12:50",
            "2. sep 08:55"
        ]
    }
}